LICENSE
README.md
setup.py
kim/__init__.py
kim/_keepinmind.py
kim/exception.py
kim/_root/__init__.py
kim/_utils/__init__.py
kim/_utils/path.py
kim/_utils/verify.py
kim_python.egg-info/PKG-INFO
kim_python.egg-info/SOURCES.txt
kim_python.egg-info/dependency_links.txt
kim_python.egg-info/top_level.txt